limigrations/__init__.py
limigrations/limigrations.py
limigrations/migration.py
limigrations-1.1.1.dist-info/AUTHORS
limigrations-1.1.1.dist-info/LICENSE.md
limigrations-1.1.1.dist-info/METADATA
limigrations-1.1.1.dist-info/WHEEL
limigrations-1.1.1.dist-info/entry_points.txt
limigrations-1.1.1.dist-info/top_level.txt
limigrations-1.1.1.dist-info/RECORD
