Metadata-Version: 2.1
Name: limigrations
Version: 1.1.1
Summary: Lightweight migrations system for python / sqlite3
Home-page: https://github.com/dragosthealex/limigrations
Author: Alex Radu
Author-email: alex.radu.1000@gmail.com
License: MIT
Keywords: migrations sqlite3 database development version-control
Platform: UNKNOWN
Classifier: Development Status :: 5 - Production/Stable
Classifier: Intended Audience :: Developers
Classifier: Topic :: Software Development :: Build Tools
Classifier: Topic :: Database
Classifier: Topic :: Software Development :: Version Control
Classifier: Topic :: Utilities
Classifier: License :: OSI Approved :: MIT License
Classifier: Natural Language :: English
Classifier: Programming Language :: Python :: 2.7
Classifier: Programming Language :: Python :: 3
Classifier: Programming Language :: Python :: 3.3
Classifier: Programming Language :: Python :: 3.4
Classifier: Programming Language :: Python :: 3.5
